plugs_contact/__init__.py
plugs_contact/admin.py
plugs_contact/emails.py
plugs_contact/models.py
plugs_contact/runtests.py
plugs_contact/serializers.py
plugs_contact/views.py
plugs_contact/migrations/0001_initial.py
plugs_contact/migrations/__init__.py
plugs_contact/templates/emails/contact_created_en.html
plugs_contact/templates/emails/contact_created_pt.html
plugs_contact/templates/emails/contact_received_en.html
plugs_contact/templates/emails/contact_received_pt.html
plugs_contact/tests/__init__.py
plugs_contact/tests/test_settings.py
plugs_contact/tests/test_views.py
plugs_contact-0.2.0.dist-info/DESCRIPTION.rst
plugs_contact-0.2.0.dist-info/METADATA
plugs_contact-0.2.0.dist-info/RECORD
plugs_contact-0.2.0.dist-info/WHEEL
plugs_contact-0.2.0.dist-info/metadata.json
plugs_contact-0.2.0.dist-info/top_level.txt
