Metadata-Version: 2.0
Name: plugs-contact
Version: 0.2.0
Summary: APP to manage contact forms
Home-page: https://github.com/solocompt/plugs-contact
Author: Solo
Author-email: geral@solo.com.pt
License: MIT
Keywords: plugs-contact
Platform: UNKNOWN
Classifier: Development Status :: 3 - Alpha
Classifier: Framework :: Django :: 1.11
Classifier: Intended Audience :: Developers
Classifier: License :: OSI Approved :: MIT License
Classifier: Natural Language :: English
Classifier: Programming Language :: Python :: 3
Requires-Dist: plugs-auth (<1.0.0,>=0.1.5)
Requires-Dist: plugs-core (<1.0.0,>=0.1.0)
Requires-Dist: plugs-mail (<1.0.0,>=0.1.5)
